skml_json/__init__.py
skml_json/classification.py
skml_json/csr.py
skml_json/regression.py
skml_json-1.0.2.dist-info/LICENSE
skml_json-1.0.2.dist-info/METADATA
skml_json-1.0.2.dist-info/WHEEL
skml_json-1.0.2.dist-info/top_level.txt
skml_json-1.0.2.dist-info/RECORD
