Metadata-Version: 2.1
Name: skml-json
Version: 1.0.2
Summary: Export scikit-learn>=1.4.0 model files to JSON for sharing or deploying predictive models with peace of mind. Original by Mathieu Rodrigue
Author-email: Sadio <sadio.ousmane@esp.sn>
License: MIT License
Project-URL: Homepage, https://github.com/osadio/skml-json
Keywords: sklearn,json
Classifier: License :: OSI Approved :: MIT License
Classifier: Programming Language :: Python
Classifier: Programming Language :: Python :: 3
Requires-Python: >=3.12
License-File: LICENSE
Requires-Dist: scikit-learn >=1.4.0
